gatecoin_api/__init__.py
gatecoin_api/api.py
gatecoin_api/constants.py
gatecoin_api/request.py
gatecoin_api/schemas.py
gatecoin_api/types.py
gatecoin_api-1.0.0.dist-info/METADATA
gatecoin_api-1.0.0.dist-info/RECORD
gatecoin_api-1.0.0.dist-info/WHEEL
gatecoin_api-1.0.0.dist-info/top_level.txt
