Metadata-Version: 2.1
Name: gatecoin-api
Version: 1.0.0
Summary: A simple GateCoin REST API client
Home-page: https://github.com/gatecoin/api-gatecoin-python
Author: Ahmed Belal
Author-email: contact@gatecoin.com
License: UNKNOWN
Platform: UNKNOWN
Classifier: Programming Language :: Python
Classifier: Programming Language :: Python :: 3
Classifier: Programming Language :: Python :: 3.3
Classifier: Programming Language :: Python :: 3.4
Classifier: Programming Language :: Python :: 3.5
Classifier: Programming Language :: Python :: 3.6
Classifier: Programming Language :: Python :: 3.7
Classifier: License :: OSI Approved :: MIT License
Classifier: Operating System :: OS Independent
Requires-Dist: requests
Requires-Dist: marshmallow
Requires-Dist: pytz
